line_integral_convolutions/__init__.py
line_integral_convolutions/fields.py
line_integral_convolutions/lic.py
line_integral_convolutions/utils.py
line_integral_convolutions-1.0.7.dist-info/LICENSE.md
line_integral_convolutions-1.0.7.dist-info/METADATA
line_integral_convolutions-1.0.7.dist-info/WHEEL
line_integral_convolutions-1.0.7.dist-info/top_level.txt
line_integral_convolutions-1.0.7.dist-info/RECORD
