Metadata-Version: 2.1
Name: line-integral-convolutions
Version: 1.0.7
Summary: My implementation of line integral convolution (LIC).
Home-page: https://github.com/AstroKriel/line-integral-convolutions/tree/main
Author: Neco Kriel
Author-email: neco.kriel@anu.edu.au
Classifier: Programming Language :: Python :: 3
Classifier: License :: OSI Approved :: MIT License
Classifier: Operating System :: OS Independent
Requires-Python: >=3.6
License-File: LICENSE.md
Requires-Dist: matplotlib<4.0,>=3.10.0
Requires-Dist: numba<1.0,>=0.60.0
Requires-Dist: numpy<3.0,>=2.0.2
Requires-Dist: scikit-image<1.0,>=0.25.0
Requires-Dist: scipy<2.0,>=1.14.1
Requires-Dist: build<2.0,>=1.2.2
Requires-Dist: twine<7.0,>=6.0.1
